Metadata-Version: 1.0
Name: tapeterm
Version: 0.2.1
Summary: Listen kasetophono's playlists from your terminal
Home-page: https://github.com/sp1thas/tapeterm
Author: Panagiotis Simakis
Author-email: sp1thas@autistici.org
License: MIT
Keywords: kasetophono
Platform: UNKNOWN
